netimages/__init__.py
netimages/__main__.py
netimages/extractor.py
netimages/render.py
netimages-0.2.0.dist-info/LICENSE
netimages-0.2.0.dist-info/WHEEL
netimages-0.2.0.dist-info/METADATA
netimages-0.2.0.dist-info/RECORD
