Metadata-Version: 2.1
Name: netimages
Version: 0.2.0
Summary: NetImages - tool for sniffing images over HTTP traffic and showing them on the console.
Home-page: https://github.com/tonybaloney/netimages
License: UNKNOWN
Keywords: security,testing
Author: Anthony Shaw
Author-email: anthonyshaw@apache.org
Requires-Python: >=3.5
Classifier: License :: OSI Approved :: Apache Software License
Requires-Dist: scapy
Requires-Dist: Pillow
Requires-Dist: ansicolors
